cubicweb_simplefacet/__init__.py
cubicweb_simplefacet/__pkginfo__.py
cubicweb_simplefacet/uiprops.py
cubicweb_simplefacet/data/cubes.simplefacet.css
cubicweb_simplefacet/data/cubes.simplefacet.js
cubicweb_simplefacet/i18n/de.po
cubicweb_simplefacet/i18n/en.po
cubicweb_simplefacet/i18n/es.po
cubicweb_simplefacet/i18n/fr.po
cubicweb_simplefacet/migration/postcreate.py
cubicweb_simplefacet/views/__init__.py
cubicweb_simplefacet/views/facets.py
cubicweb_simplefacet/views/views.py
cubicweb_simplefacet-2.0.0.dist-info/METADATA
cubicweb_simplefacet-2.0.0.dist-info/WHEEL
cubicweb_simplefacet-2.0.0.dist-info/entry_points.txt
cubicweb_simplefacet-2.0.0.dist-info/top_level.txt
cubicweb_simplefacet-2.0.0.dist-info/RECORD
