Metadata-Version: 2.1
Name: cubicweb-simplefacet
Version: 2.0.0
Summary: Cube adding another display for facets.
Home-page: https://forge.extranet.logilab.fr/cubicweb/cubes/cubicweb-simplefacet
Author: LOGILAB S.A. (Paris, FRANCE)
Author-email: contact@logilab.fr
License: LGPL
Platform: UNKNOWN
Classifier: Environment :: Web Environment
Classifier: Framework :: CubicWeb
Classifier: Programming Language :: Python :: 3
Classifier: Programming Language :: JavaScript
Requires-Dist: cubicweb (<3.39.0,>=3.38.0)
